myhan/__init__.py
myhan-0.0.1.dist-info/METADATA
myhan-0.0.1.dist-info/WHEEL
myhan-0.0.1.dist-info/top_level.txt
myhan-0.0.1.dist-info/RECORD
