Metadata-Version: 2.1
Name: myhan
Version: 0.0.1
Summary: My first Python package
Author: myname
Keywords: python,first package
Classifier: Intended Audience :: Education
Classifier: Programming Language :: Python :: 3
Classifier: Operating System :: Microsoft :: Windows
